{
  "db_name": "PostgreSQL",
  "query": "\nSELECT id, name, official_name, osm_name, short_name, locality, street, door,\n    lat, lon, notes, update_date, parish, tags, accessibility_meta,\n    verification_level, service_check_date, infrastructure_check_date\nFROM Stops\nWHERE lon >= $1 AND lon <= $2 AND lat <= $3 AND lat >= $4 AND id IN (\n    SELECT DISTINCT stop FROM subroute_stops\n)\n        ",
  "describe": {
    "columns": [
      {
        "ordinal": 0,
        "name": "id",
        "type_info": "Int4"
      },
      {
        "ordinal": 1,
        "name": "name",
        "type_info": "Varchar"
      },
      {
        "ordinal": 2,
        "name": "official_name",
        "type_info": "Varchar"
      },
      {
        "ordinal": 3,
        "name": "osm_name",
        "type_info": "Varchar"
      },
      {
        "ordinal": 4,
        "name": "short_name",
        "type_info": "Varchar"
      },
      {
        "ordinal": 5,
        "name": "locality",
        "type_info": "Varchar"
      },
      {
        "ordinal": 6,
        "name": "street",
        "type_info": "Varchar"
      },
      {
        "ordinal": 7,
        "name": "door",
        "type_info": "Varchar"
      },
      {
        "ordinal": 8,
        "name": "lat",
        "type_info": "Float8"
      },
      {
        "ordinal": 9,
        "name": "lon",
        "type_info": "Float8"
      },
      {
        "ordinal": 10,
        "name": "notes",
        "type_info": "Varchar"
      },
      {
        "ordinal": 11,
        "name": "update_date",
        "type_info": "Text"
      },
      {
        "ordinal": 12,
        "name": "parish",
        "type_info": "Int4"
      },
      {
        "ordinal": 13,
        "name": "tags",
        "type_info": "VarcharArray"
      },
      {
        "ordinal": 14,
        "name": "accessibility_meta",
        "type_info": "Jsonb"
      },
      {
        "ordinal": 15,
        "name": "verification_level",
        "type_info": "Int2"
      },
      {
        "ordinal": 16,
        "name": "service_check_date",
        "type_info": "Date"
      },
      {
        "ordinal": 17,
        "name": "infrastructure_check_date",
        "type_info": "Date"
      }
    ],
    "parameters": {
      "Left": [
        "Float8",
        "Float8",
        "Float8",
        "Float8"
      ]
    },
    "nullable": [
      false,
      true,
      true,
      true,
      true,
      true,
      true,
      true,
      true,
      true,
      true,
      false,
      true,
      false,
      false,
      false,
      true,
      true
    ]
  },
  "hash": "5ca97c4babf1be58fa5dcb5b415467b3dc65d0049a3a9a4f3513f95745b8a561"
}
