{
  "db_name": "PostgreSQL",
  "query": "\nSELECT id, username, password, email, is_admin, is_trusted, works_for\nFROM Users\nWHERE username=$1 or email = $2\n    ",
  "describe": {
    "columns": [
      {
        "ordinal": 0,
        "name": "id",
        "type_info": "Int4"
      },
      {
        "ordinal": 1,
        "name": "username",
        "type_info": "Text"
      },
      {
        "ordinal": 2,
        "name": "password",
        "type_info": "Text"
      },
      {
        "ordinal": 3,
        "name": "email",
        "type_info": "Text"
      },
      {
        "ordinal": 4,
        "name": "is_admin",
        "type_info": "Bool"
      },
      {
        "ordinal": 5,
        "name": "is_trusted",
        "type_info": "Bool"
      },
      {
        "ordinal": 6,
        "name": "works_for",
        "type_info": "Int4"
      }
    ],
    "parameters": {
      "Left": [
        "Text",
        "Text"
      ]
    },
    "nullable": [
      false,
      false,
      false,
      false,
      false,
      false,
      true
    ]
  },
  "hash": "d7f6a5ad58f175174586daa9da649d7b550431c521a6f535ae8da8fc4e4a0e98"
}
